pykit/__init__.py
pykit/logging/__init__.py
pykit/logging/logger.py
riso_pykit-0.1.0.dist-info/METADATA
riso_pykit-0.1.0.dist-info/WHEEL
riso_pykit-0.1.0.dist-info/top_level.txt
riso_pykit-0.1.0.dist-info/RECORD
