Metadata-Version: 2.4
Name: riso-pykit
Version: 0.1.0
Summary: RisoTech Python Kit - A collection of Python tools and libraries for the Riso framework
Author-email: Bin Nguyen <tu.nguyen@risotech.vn>
Project-URL: Homepage, https://github.com/libs-factory/riso-pykit
Project-URL: Documentation, https://github.com/libs-factory/riso-pykit#readme
Project-URL: Repository, https://github.com/libs-factory/riso-pykit
Project-URL: Bug Tracker, https://github.com/libs-factory/riso-pykit/issues
Keywords: riso,pykit,risotech,python,toolkit,utilities,logger
Classifier: Development Status :: 3 - Alpha
Classifier: Intended Audience :: Developers
Classifier: License :: OSI Approved :: MIT License
Classifier: Operating System :: OS Independent
Classifier: Programming Language :: Python
Classifier: Programming Language :: Python :: 3
Classifier: Programming Language :: Python :: 3.12
Requires-Python: >=3.12
Requires-Dist: build==1.2.2
Requires-Dist: twine==6.0.1
Requires-Dist: ruff==0.13.0
Requires-Dist: pre-commit==4.3.0
Requires-Dist: ipdb==0.13.13
Requires-Dist: pytest==8.3.4
Requires-Dist: pytest-cov==6.0.0
